COPYING.txt
LISEZMOI.txt
MANIFEST.in
Makefile
README.txt
msgfmt.py
setup.py
debian/changelog
debian/control
debian/copyright
debian/dnuos.1.fr.pod
debian/dnuos.1.pod
debian/docs
debian/rules
debian/watch
dnuos/__init__.py
dnuos/appdata.py
dnuos/audiodir.py
dnuos/audiotype.py
dnuos/conf.py
dnuos/misc.py
dnuos/path.py
dnuos.egg-info/PKG-INFO
dnuos.egg-info/SOURCES.txt
dnuos.egg-info/dependency_links.txt
dnuos.egg-info/not-zip-safe
dnuos.egg-info/top_level.txt
dnuos/cache/__init__.py
dnuos/cache/shelvecache.py
dnuos/cache/sqlitecache.py
dnuos/id3/ID3v2Frames.py
dnuos/id3/__init__.py
dnuos/id3/binfuncs.py
dnuos/locale/dnuos.pot
dnuos/locale/fr/LC_MESSAGES/dnuos.po
dnuos/output/__init__.py
dnuos/output/abstract_renderer.py
dnuos/output/db.py
dnuos/output/html.py
dnuos/output/plaintext.py
dnuostests/__init__.py
dnuostests/basedirs.py
dnuostests/bitrate.py
dnuostests/broken.py
dnuostests/cache.py
dnuostests/case.py
dnuostests/default.py
dnuostests/exclude.py
dnuostests/functest.py
dnuostests/ignorebad.py
dnuostests/indent.py
dnuostests/lameonly.py
dnuostests/listfiles.py
dnuostests/merge.py
dnuostests/mixed.py
dnuostests/noargs.py
dnuostests/nomerge.py
dnuostests/outputdb_new.py
dnuostests/prefertag.py
dnuostests/strip.py
dnuostests/tag_a.py
dnuostests/tag_b.py
dnuostests/tag_f.py
dnuostests/tag_l.py
dnuostests/tag_m.py
dnuostests/tag_n.py
dnuostests/tag_p.py
dnuostests/tag_q.py
dnuostests/tag_s.py
dnuostests/tag_t.py
dnuostests/tag_upper_a.py
dnuostests/tag_upper_b.py
dnuostests/tag_upper_c.py
dnuostests/tag_upper_d.py
dnuostests/tag_upper_l.py
dnuostests/tag_upper_m.py
dnuostests/tag_upper_n.py
dnuostests/tag_upper_p.py
dnuostests/tag_upper_s.py
dnuostests/tag_upper_t.py
dnuostests/tag_upper_v.py
dnuostests/unknown.py
dnuostests/vbronly.py
dnuostests/version.py
dnuostests/wildcards.py
scripts/dnuos