Metadata-Version: 1.0
Name: dnuos
Version: 1.0.11
Summary: A tool for creating lists of music collections
Home-page: http://bitheap.org/dnuos/
Author: Mattias Päivärinta, Brodie Rao
Author-email: pejve@vasteras2.net; brodie@bitheap.org
License: GNU GPL
Download-URL: http://bitheap.org/dnuos/files/dnuos-1.0.11.tar.gz
Keywords: music collection list metadata mp3 audiolist oidua
Platform: UNKNOWN
Classifier: Development Status :: 5 - Production/Stable
Classifier: Environment :: Console
Classifier: Intended Audience :: End Users/Desktop
Classifier: License :: OSI Approved :: GNU General Public License (GPL)
Classifier: Natural Language :: English
Classifier: Natural Language :: French
Classifier: Operating System :: OS Independent
Classifier: Topic :: Communications :: File Sharing
Classifier: Topic :: Multimedia :: Sound/Audio
